streamfield/__init__.py
streamfield/admin.py
streamfield/apps.py
streamfield/base.py
streamfield/fields.py
streamfield/forms.py
streamfield/models.py
streamfield/settings.py
streamfield/tests.py
streamfield/urls.py
streamfield/views.py
streamfield/locale/en/LC_MESSAGES/django.mo
streamfield/locale/en/LC_MESSAGES/django.po
streamfield/locale/fr/LC_MESSAGES/django.mo
streamfield/locale/fr/LC_MESSAGES/django.po
streamfield/locale/it/LC_MESSAGES/django.mo
streamfield/locale/it/LC_MESSAGES/django.po
streamfield/locale/ru/LC_MESSAGES/django.mo
streamfield/locale/ru/LC_MESSAGES/django.po
streamfield/static/.DS_Store
streamfield/static/streamfield/admin_popup_response.js
streamfield/static/streamfield/streamfield_widget.css
streamfield/static/streamfield/streamfield_widget.js
streamfield/templates/streamfield/default_block_tmpl.html
streamfield/templates/streamfield/streamfield_admin_help.html
streamfield/templates/streamfield/streamfield_texts.js
streamfield/templates/streamfield/streamfield_widget.html
streamfield/templates/streamfield/admin/abstract_block_template.html
streamfield/templates/streamfield/admin/change_form.html
streamfield/templates/streamfield/admin/change_form_render_template.html
streamfield/templates/streamfield/admin/streamfield_popup_response.html
streamfield/templates/streamfield/admin/fields/default.html
streamfield/templates/streamfield/admin/fields/file_browse_widget.html
streamfield/templates/streamfield/admin/fields/select.html
streamfield/templates/streamfield/admin/fields/stream_field_widget.html
streamfield/templatetags/__init__.py
streamfield/templatetags/streamfield_tags.py
django_streamfield-2.4.0.dist-info/LICENSE
django_streamfield-2.4.0.dist-info/METADATA
django_streamfield-2.4.0.dist-info/WHEEL
django_streamfield-2.4.0.dist-info/top_level.txt
django_streamfield-2.4.0.dist-info/RECORD
