Metadata-Version: 2.1
Name: django-streamfield
Version: 2.4.0
Summary: StreamField for native Django Admin or with Grappelli
Home-page: https://github.com/raagin/django-streamfield
Author: Yury Lapshinov
Author-email: y.raagin@gmail.com
Classifier: Development Status :: 5 - Production/Stable
Classifier: License :: OSI Approved :: BSD License
Classifier: Operating System :: OS Independent
Classifier: Programming Language :: Python
Classifier: Programming Language :: Python :: 3.10
Classifier: Programming Language :: Python :: 3.11
Classifier: Programming Language :: Python :: 3.12
Classifier: Framework :: Django
Classifier: Framework :: Django :: 4.2
Classifier: Framework :: Django :: 5.0
Classifier: Framework :: Django :: 5.1
Classifier: Framework :: Django :: 5.2
Requires-Python: >=3.10
License-File: LICENSE
